aotpy/__init__.py
aotpy/core/__init__.py
aotpy/core/aberration.py
aotpy/core/ao_system.py
aotpy/core/atmosphere.py
aotpy/core/base.py
aotpy/core/image.py
aotpy/core/loop.py
aotpy/core/optical_sensor.py
aotpy/core/source.py
aotpy/core/telescope.py
aotpy/core/time.py
aotpy/core/wavefront_corrector.py
aotpy/data/__init__.py
aotpy/data/ERIS/ho_subap.fits
aotpy/data/ERIS/lo_subap.fits
aotpy/data/GALACSI/subap.fits
aotpy/data/NAOMI/zernike_control_modes.fits
aotpy/data/PAPYRUS/T152_pupil.fits
aotpy/data/PAPYRUS/max_pupil_mask.fits
aotpy/io/__init__.py
aotpy/io/base.py
aotpy/io/fits/__init__.py
aotpy/io/fits/_file.py
aotpy/io/fits/_strings.py
aotpy/io/fits/compat.py
aotpy/io/fits/reader.py
aotpy/io/fits/utils.py
aotpy/io/fits/writer.py
aotpy/translators/__init__.py
aotpy/translators/base.py
aotpy/translators/ciao.py
aotpy/translators/eris.py
aotpy/translators/eso.py
aotpy/translators/galacsi.py
aotpy/translators/gpao.py
aotpy/translators/naomi.py
aotpy/translators/papyrus.py
aotpy-3.2.1.dist-info/licenses/LICENSE
aotpy-3.2.1.dist-info/METADATA
aotpy-3.2.1.dist-info/WHEEL
aotpy-3.2.1.dist-info/top_level.txt
aotpy-3.2.1.dist-info/RECORD
