Metadata-Version: 2.4
Name: aotpy
Version: 3.2.1
Summary: Helper package for handling Adaptive Optics Telemetry (AOT) standard files
Author-email: Tiago Gomes <tiagogomes@fe.up.pt>
License-Expression: BSD-3-Clause
Project-URL: Repository, https://github.com/STAR-PORT/aotpy
Project-URL: Issues, https://github.com/STAR-PORT/aotpy/issues
Project-URL: Documentation, https://aotpy.readthedocs.io/
Keywords: Adaptive Optics,Telemetry,Data Exchange Format,AOT,FITS,PSF Reconstruction,Atmospheric Turbulence
Classifier: Development Status :: 4 - Beta
Classifier: Intended Audience :: Science/Research
Classifier: Programming Language :: Python :: 3
Classifier: Operating System :: OS Independent
Classifier: Topic :: File Formats
Classifier: Topic :: Scientific/Engineering :: Astronomy
Requires-Python: >=3.10
License-File: LICENSE
Requires-Dist: astropy>=5.1.1
Requires-Dist: numpy>=1.20
Provides-Extra: esoarchive
Requires-Dist: pyvo>=1.4; extra == "esoarchive"
Provides-Extra: savfiles
Requires-Dist: scipy>=1.5.0; extra == "savfiles"
Provides-Extra: docs
Requires-Dist: sphinx; extra == "docs"
Requires-Dist: sphinx-rtd-theme; extra == "docs"
Provides-Extra: all
Requires-Dist: pyvo>=1.4; extra == "all"
Requires-Dist: scipy>=1.5.0; extra == "all"
Dynamic: license-file
